odoo/addons/endpoint_cache/README.rst
odoo/addons/endpoint_cache/__init__.py
odoo/addons/endpoint_cache/__manifest__.py
odoo/addons/endpoint_cache/i18n/endpoint_cache.pot
odoo/addons/endpoint_cache/i18n/it.po
odoo/addons/endpoint_cache/models/__init__.py
odoo/addons/endpoint_cache/models/endpoint_mixin.py
odoo/addons/endpoint_cache/readme/CONTRIBUTORS.md
odoo/addons/endpoint_cache/readme/DESCRIPTION.md
odoo/addons/endpoint_cache/readme/USAGE.md
odoo/addons/endpoint_cache/static/description/icon.png
odoo/addons/endpoint_cache/static/description/index.html
odoo/addons/endpoint_cache/tests/__init__.py
odoo/addons/endpoint_cache/tests/test_endpoint.py
odoo/addons/endpoint_cache/views/endpoint_view.xml
odoo_addon_endpoint_cache-18.0.1.0.0.2.dist-info/METADATA
odoo_addon_endpoint_cache-18.0.1.0.0.2.dist-info/WHEEL
odoo_addon_endpoint_cache-18.0.1.0.0.2.dist-info/top_level.txt
odoo_addon_endpoint_cache-18.0.1.0.0.2.dist-info/RECORD
